DigitalDesign_exercises/Combinational/Exercises/4.6/4_6.v
// DataFlow model of ex 4_6
module ex4_6(x,y,z,F);
	input x,y,z;
	output F;
	wire F1,F2,F3;
	assign F1=(x&y);
	assign F2=(y&z);
	assign F3=(z&x);
	assign F=(F1|F2|F3);
endmodule

DigitalDesign_exercises/Combinational/Exercises/4.6/test_ex4_6.v
// test bench

module testbench;
	reg x,y,z;
	wire F;
	integer i;
// module instantiation
ex4_6 test1(x,y,z,F);
	initial
		begin
		$dumpfile("test1.vcd");
		$dumpvars(0,testbench);
		$monitor($time,"x=%b,y=%b,z=%b,F=%b",x,y,z,F);
			for(i=0;i<8;i++)
				begin
					{x,y,z}=i;
					#5;
			end
			#5 $finish;
			end
endmodule

DigitalDesign_exercises/Combinational/Exercises/4.6/test1.vcd
$date
	Mon Sep 07 08:24:24 2020
$end
$version
	Icarus Verilog
$end
$timescale
	1s
$end
$scope module testbench $end
$var wire 1 ! F $end
$var reg 1 " x $end
$var reg 1 # y $end
$var reg 1 $ z $end
$var integer 32 % i [31:0] $end
$scope module test1 $end
$var wire 1 ! F $end
$var wire 1 & F1 $end
$var wire 1 ' F2 $end
$var wire 1 ( F3 $end
$var wire 1 " x $end
$var wire 1 # y $end
$var wire 1 $ z $end
$upscope $end
$upscope $end
$enddefinitions $end
#0
$dumpvars
0(
0'
0&
b0 %
0$
0#
0"
0!
$end
#5
1$
b1 %
#10
1#
0$
b10 %
#15
1!
1'
1$
b11 %
#20
0!
0'
1"
0#
0$
b100 %
#25
1!
1(
1$
b101 %
#30
1!
1&
0(
1#
0$
b110 %
#35
1'
1(
1$
b111 %
#40
b1000 %
