DigitalDesign_exercises/Combinational/Exercises/4.10/4_10.v
// 4 bit combinational circuit 2's complementer
module two_complement(input w,x,y,z, output a,b,c,d);
	wire t1,t2,t3,t4,t5;
	
// Behavioral description of 2's complementer - Gate Level
	or(t1,x,y);
	or(t2,t1,z);
	xor(t3,x,y);
	and(t4,t3,~z);
	and(t5,~x,z);
	xor(a,w,t2);
	or(b,t4,t5);
	xor(c,y,z);
	buf(d,z);
endmodule


// TestBench

module test;

wire a,b,c,d;
reg w,x,y,z;
integer i;
// Instantiate DUT
	two_complement tc1(w,x,y,z,a,b,c,d);
	
	initial
		begin
			$dumpfile("two_complement.vcd");
			$dumpvars(0,test);
			$monitor("%d ",$time,"%b%b%b%b %b%b%b%b",w,x,y,z,a,b,c,d);
			for(i=0;i<16;i++)
				begin
					{w,x,y,z}={i};
					#5;
					end
		end
endmodule

DigitalDesign_exercises/Combinational/Exercises/4.10/two_complement.vcd
$date
	Thu Sep 17 09:15:33 2020
$end
$version
	Icarus Verilog
$end
$timescale
	1s
$end
$scope module test $end
$var wire 1 ! d $end
$var wire 1 " c $end
$var wire 1 # b $end
$var wire 1 $ a $end
$var reg 1 % w $end
$var reg 1 & x $end
$var reg 1 ' y $end
$var reg 1 ( z $end
$var integer 32 ) i [31:0] $end
$scope module tc1 $end
$var wire 1 $ a $end
$var wire 1 # b $end
$var wire 1 " c $end
$var wire 1 ! d $end
$var wire 1 * t1 $end
$var wire 1 + t2 $end
$var wire 1 , t3 $end
$var wire 1 - t4 $end
$var wire 1 . t5 $end
$var wire 1 % w $end
$var wire 1 & x $end
$var wire 1 ' y $end
$var wire 1 ( z $end
$upscope $end
$upscope $end
$enddefinitions $end
#0
$dumpvars
0.
0-
0,
0+
0*
b0 )
0(
0'
0&
0%
0$
0#
0"
0!
$end
#5
1$
1#
1+
1.
1"
1!
1(
b1 )
#10
1$
1-
1#
1*
1,
1+
0.
0!
1'
0(
b10 )
#15
0-
1.
0"
1!
1(
b11 )
#20
1-
1#
0.
0!
1&
0'
0(
b100 )
#25
0#
0-
1"
1!
1(
b101 )
#30
0,
0!
1'
0(
b110 )
#35
0"
1!
1(
b111 )
#40
0+
1$
0*
0!
1%
0&
0'
0(
b1000 )
#45
0$
1#
1+
1.
1"
1!
1(
b1001 )
#50
0$
1-
1#
1*
1,
1+
0.
0!
1'
0(
b1010 )
#55
0-
1.
0"
1!
1(
b1011 )
#60
1-
1#
0.
0!
1&
0'
0(
b1100 )
#65
0#
0-
1"
1!
1(
b1101 )
#70
0,
0!
1'
0(
b1110 )
#75
0"
1!
1(
b1111 )
#80
b10000 )
