Sequential_Circuits/Serializer/shiftreg_16bit.v
// 4 bit shift register using D Flip Flops
`timescale 1ns/10ps

module shiftreg_16bit(input clk,clear,
					  input A,
					  output reg[N:0]E);
	/*input clk, clear,A;
	output reg E;
	reg B,C,D;
	*/
	// beginning of behavioral description of the shift register
	parameter N=15;
	integer i;
	always @ (posedge clk or negedge clk)
		begin
			if(!clear)
				begin
				for(i=N-1;i>=0;i--)
				begin
				E[N:0]<=0;
				end
				end
			else
				begin
					for(i=N;i>=0;i--)
					begin
					E[N]<=E[N-1];
					E[N-1]<=E[N-2];
					E[N-2]<=E[N-3];
					E[N-3]<=E[N-4];
					E[N-4]<=E[N-5];
					E[N-5]<=E[N-6];
					E[N-6]<=E[N-7];
					E[N-7]<=E[N-8];
					E[N-8]<=E[N-9];
					E[N-9]<=E[N-10];
					E[N-10]<=E[N-11];
					E[N-11]<=E[N-12];
					E[N-12]<=E[N-13];
					E[N-13]<=E[N-14];
					E[N-14]<=E[N-15];
					E[N-15]<=A;	
					end
				end
		end
	endmodule

// test bench

// Test bench for shift register 4-bit

module test_bench;
	reg clr,clk,in;
	wire [N:0]out;
	parameter N=15;

// Instantiate a 4bit shift register
shiftreg_16bit SR(.clk(clk), .clear(clr), .A(in), .E(out));
// code for testbench begins here
initial
	begin
		clk =1'b0;
		#2 clr =0;
		#3 clr =1;
		end
// All the flip flops have been cleared after the previous operation. Now we need to simulate clock signal.
always #5 clk =~clk;  // This line toggles the clock signal between 0 and 1 every 5 intervals.

// Input test bit pattern - 1100
initial
	begin
		#2;
		repeat(2) // repeat the block for 2 times
			
		begin
			#10 in=0;
			#10 in = 0;
			#10 in = 1;
			#10 in =1;
			end
			end
	initial
		begin
		$monitor($time,"E: %4h",out);
		$dumpfile("test_shifter.vcd");
		$dumpvars(0,test_bench);
		#1000 $finish;
	end
endmodule

Sequential_Circuits/Serializer/test_shifter.vcd
$date
	Wed Dec 16 12:01:53 2020
$end
$version
	Icarus Verilog
$end
$timescale
	10ps
$end
$scope module test_bench $end
$var wire 16 ! out [15:0] $end
$var reg 1 " clk $end
$var reg 1 # clr $end
$var reg 1 $ in $end
$scope module SR $end
$var wire 1 $ A $end
$var wire 1 # clear $end
$var wire 1 " clk $end
$var reg 16 % E [15:0] $end
$var integer 32 & i [31:0] $end
$upscope $end
$upscope $end
$enddefinitions $end
#0
$dumpvars
b11111111111111111111111111111111 &
bx %
x$
x#
0"
bx !
$end
#200
0#
#500
b11111111111111111111111111111111 &
1#
1"
#1000
b11111111111111111111111111111111 &
0"
#1200
0$
#1500
bx0 !
bx0 %
b11111111111111111111111111111111 &
1"
#2000
bx00 !
bx00 %
b11111111111111111111111111111111 &
0"
#2500
bx000 !
bx000 %
b11111111111111111111111111111111 &
1"
#3000
bx0000 !
bx0000 %
b11111111111111111111111111111111 &
0"
#3200
1$
#3500
bx00001 !
bx00001 %
b11111111111111111111111111111111 &
1"
#4000
bx000011 !
bx000011 %
b11111111111111111111111111111111 &
0"
#4500
bx0000111 !
bx0000111 %
b11111111111111111111111111111111 &
1"
#5000
bx00001111 !
bx00001111 %
b11111111111111111111111111111111 &
0"
#5200
0$
#5500
bx000011110 !
bx000011110 %
b11111111111111111111111111111111 &
1"
#6000
bx0000111100 !
bx0000111100 %
b11111111111111111111111111111111 &
0"
#6500
bx00001111000 !
bx00001111000 %
b11111111111111111111111111111111 &
1"
#7000
bx000011110000 !
bx000011110000 %
b11111111111111111111111111111111 &
0"
#7200
1$
#7500
bx0000111100001 !
bx0000111100001 %
b11111111111111111111111111111111 &
1"
#8000
bx00001111000011 !
bx00001111000011 %
b11111111111111111111111111111111 &
0"
#8500
bx000011110000111 !
bx000011110000111 %
b11111111111111111111111111111111 &
1"
#9000
b111100001111 !
b111100001111 %
b11111111111111111111111111111111 &
0"
#9500
b1111000011111 !
b1111000011111 %
b11111111111111111111111111111111 &
1"
#10000
b11110000111111 !
b11110000111111 %
b11111111111111111111111111111111 &
0"
#10500
b111100001111111 !
b111100001111111 %
b11111111111111111111111111111111 &
1"
#11000
b1111000011111111 !
b1111000011111111 %
b11111111111111111111111111111111 &
0"
#11500
b1110000111111111 !
b1110000111111111 %
b11111111111111111111111111111111 &
1"
#12000
b1100001111111111 !
b1100001111111111 %
b11111111111111111111111111111111 &
0"
#12500
b1000011111111111 !
b1000011111111111 %
b11111111111111111111111111111111 &
1"
#13000
b111111111111 !
b111111111111 %
b11111111111111111111111111111111 &
0"
#13500
b1111111111111 !
b1111111111111 %
b11111111111111111111111111111111 &
1"
#14000
b11111111111111 !
b11111111111111 %
b11111111111111111111111111111111 &
0"
#14500
b111111111111111 !
b111111111111111 %
b11111111111111111111111111111111 &
1"
#15000
b1111111111111111 !
b1111111111111111 %
b11111111111111111111111111111111 &
0"
#15500
b11111111111111111111111111111111 &
1"
#16000
b11111111111111111111111111111111 &
0"
#16500
b11111111111111111111111111111111 &
1"
#17000
b11111111111111111111111111111111 &
0"
#17500
b11111111111111111111111111111111 &
1"
#18000
b11111111111111111111111111111111 &
0"
#18500
b11111111111111111111111111111111 &
1"
#19000
b11111111111111111111111111111111 &
0"
#19500
b11111111111111111111111111111111 &
1"
#20000
b11111111111111111111111111111111 &
0"
#20500
b11111111111111111111111111111111 &
1"
#21000
b11111111111111111111111111111111 &
0"
#21500
b11111111111111111111111111111111 &
1"
#22000
b11111111111111111111111111111111 &
0"
#22500
b11111111111111111111111111111111 &
1"
#23000
b11111111111111111111111111111111 &
0"
#23500
b11111111111111111111111111111111 &
1"
#24000
b11111111111111111111111111111111 &
0"
#24500
b11111111111111111111111111111111 &
1"
#25000
b11111111111111111111111111111111 &
0"
#25500
b11111111111111111111111111111111 &
1"
#26000
b11111111111111111111111111111111 &
0"
#26500
b11111111111111111111111111111111 &
1"
#27000
b11111111111111111111111111111111 &
0"
#27500
b11111111111111111111111111111111 &
1"
#28000
b11111111111111111111111111111111 &
0"
#28500
b11111111111111111111111111111111 &
1"
#29000
b11111111111111111111111111111111 &
0"
#29500
b11111111111111111111111111111111 &
1"
#30000
b11111111111111111111111111111111 &
0"
#30500
b11111111111111111111111111111111 &
1"
#31000
b11111111111111111111111111111111 &
0"
#31500
b11111111111111111111111111111111 &
1"
#32000
b11111111111111111111111111111111 &
0"
#32500
b11111111111111111111111111111111 &
1"
#33000
b11111111111111111111111111111111 &
0"
#33500
b11111111111111111111111111111111 &
1"
#34000
b11111111111111111111111111111111 &
0"
#34500
b11111111111111111111111111111111 &
1"
#35000
b11111111111111111111111111111111 &
0"
#35500
b11111111111111111111111111111111 &
1"
#36000
b11111111111111111111111111111111 &
0"
#36500
b11111111111111111111111111111111 &
1"
#37000
b11111111111111111111111111111111 &
0"
#37500
b11111111111111111111111111111111 &
1"
#38000
b11111111111111111111111111111111 &
0"
#38500
b11111111111111111111111111111111 &
1"
#39000
b11111111111111111111111111111111 &
0"
#39500
b11111111111111111111111111111111 &
1"
#40000
b11111111111111111111111111111111 &
0"
#40500
b11111111111111111111111111111111 &
1"
#41000
b11111111111111111111111111111111 &
0"
#41500
b11111111111111111111111111111111 &
1"
#42000
b11111111111111111111111111111111 &
0"
#42500
b11111111111111111111111111111111 &
1"
#43000
b11111111111111111111111111111111 &
0"
#43500
b11111111111111111111111111111111 &
1"
#44000
b11111111111111111111111111111111 &
0"
#44500
b11111111111111111111111111111111 &
1"
#45000
b11111111111111111111111111111111 &
0"
#45500
b11111111111111111111111111111111 &
1"
#46000
b11111111111111111111111111111111 &
0"
#46500
b11111111111111111111111111111111 &
1"
#47000
b11111111111111111111111111111111 &
0"
#47500
b11111111111111111111111111111111 &
1"
#48000
b11111111111111111111111111111111 &
0"
#48500
b11111111111111111111111111111111 &
1"
#49000
b11111111111111111111111111111111 &
0"
#49500
b11111111111111111111111111111111 &
1"
#50000
b11111111111111111111111111111111 &
0"
#50500
b11111111111111111111111111111111 &
1"
#51000
b11111111111111111111111111111111 &
0"
#51500
b11111111111111111111111111111111 &
1"
#52000
b11111111111111111111111111111111 &
0"
#52500
b11111111111111111111111111111111 &
1"
#53000
b11111111111111111111111111111111 &
0"
#53500
b11111111111111111111111111111111 &
1"
#54000
b11111111111111111111111111111111 &
0"
#54500
b11111111111111111111111111111111 &
1"
#55000
b11111111111111111111111111111111 &
0"
#55500
b11111111111111111111111111111111 &
1"
#56000
b11111111111111111111111111111111 &
0"
#56500
b11111111111111111111111111111111 &
1"
#57000
b11111111111111111111111111111111 &
0"
#57500
b11111111111111111111111111111111 &
1"
#58000
b11111111111111111111111111111111 &
0"
#58500
b11111111111111111111111111111111 &
1"
#59000
b11111111111111111111111111111111 &
0"
#59500
b11111111111111111111111111111111 &
1"
#60000
b11111111111111111111111111111111 &
0"
#60500
b11111111111111111111111111111111 &
1"
#61000
b11111111111111111111111111111111 &
0"
#61500
b11111111111111111111111111111111 &
1"
#62000
b11111111111111111111111111111111 &
0"
#62500
b11111111111111111111111111111111 &
1"
#63000
b11111111111111111111111111111111 &
0"
#63500
b11111111111111111111111111111111 &
1"
#64000
b11111111111111111111111111111111 &
0"
#64500
b11111111111111111111111111111111 &
1"
#65000
b11111111111111111111111111111111 &
0"
#65500
b11111111111111111111111111111111 &
1"
#66000
b11111111111111111111111111111111 &
0"
#66500
b11111111111111111111111111111111 &
1"
#67000
b11111111111111111111111111111111 &
0"
#67500
b11111111111111111111111111111111 &
1"
#68000
b11111111111111111111111111111111 &
0"
#68500
b11111111111111111111111111111111 &
1"
#69000
b11111111111111111111111111111111 &
0"
#69500
b11111111111111111111111111111111 &
1"
#70000
b11111111111111111111111111111111 &
0"
#70500
b11111111111111111111111111111111 &
1"
#71000
b11111111111111111111111111111111 &
0"
#71500
b11111111111111111111111111111111 &
1"
#72000
b11111111111111111111111111111111 &
0"
#72500
b11111111111111111111111111111111 &
1"
#73000
b11111111111111111111111111111111 &
0"
#73500
b11111111111111111111111111111111 &
1"
#74000
b11111111111111111111111111111111 &
0"
#74500
b11111111111111111111111111111111 &
1"
#75000
b11111111111111111111111111111111 &
0"
#75500
b11111111111111111111111111111111 &
1"
#76000
b11111111111111111111111111111111 &
0"
#76500
b11111111111111111111111111111111 &
1"
#77000
b11111111111111111111111111111111 &
0"
#77500
b11111111111111111111111111111111 &
1"
#78000
b11111111111111111111111111111111 &
0"
#78500
b11111111111111111111111111111111 &
1"
#79000
b11111111111111111111111111111111 &
0"
#79500
b11111111111111111111111111111111 &
1"
#80000
b11111111111111111111111111111111 &
0"
#80500
b11111111111111111111111111111111 &
1"
#81000
b11111111111111111111111111111111 &
0"
#81500
b11111111111111111111111111111111 &
1"
#82000
b11111111111111111111111111111111 &
0"
#82500
b11111111111111111111111111111111 &
1"
#83000
b11111111111111111111111111111111 &
0"
#83500
b11111111111111111111111111111111 &
1"
#84000
b11111111111111111111111111111111 &
0"
#84500
b11111111111111111111111111111111 &
1"
#85000
b11111111111111111111111111111111 &
0"
#85500
b11111111111111111111111111111111 &
1"
#86000
b11111111111111111111111111111111 &
0"
#86500
b11111111111111111111111111111111 &
1"
#87000
b11111111111111111111111111111111 &
0"
#87500
b11111111111111111111111111111111 &
1"
#88000
b11111111111111111111111111111111 &
0"
#88500
b11111111111111111111111111111111 &
1"
#89000
b11111111111111111111111111111111 &
0"
#89500
b11111111111111111111111111111111 &
1"
#90000
b11111111111111111111111111111111 &
0"
#90500
b11111111111111111111111111111111 &
1"
#91000
b11111111111111111111111111111111 &
0"
#91500
b11111111111111111111111111111111 &
1"
#92000
b11111111111111111111111111111111 &
0"
#92500
b11111111111111111111111111111111 &
1"
#93000
b11111111111111111111111111111111 &
0"
#93500
b11111111111111111111111111111111 &
1"
#94000
b11111111111111111111111111111111 &
0"
#94500
b11111111111111111111111111111111 &
1"
#95000
b11111111111111111111111111111111 &
0"
#95500
b11111111111111111111111111111111 &
1"
#96000
b11111111111111111111111111111111 &
0"
#96500
b11111111111111111111111111111111 &
1"
#97000
b11111111111111111111111111111111 &
0"
#97500
b11111111111111111111111111111111 &
1"
#98000
b11111111111111111111111111111111 &
0"
#98500
b11111111111111111111111111111111 &
1"
#99000
b11111111111111111111111111111111 &
0"
#99500
b11111111111111111111111111111111 &
1"
#100000
b11111111111111111111111111111111 &
0"
