DigitalDesign_exercises/Combinational/Exercises/4.9/BCD27.v
//Verilog : 2001 :: Code for a BCD to 7 Segment display
module bcd27(input A,B,C,D,
			 output a,b,c,d,e,f,g);
		// gate level description
		assign a = ~(B^D)|(C)|(A);
		assign b = (~B)|~(C^D);
		assign c = (~C)|(D)|(B);
		assign d = ~(~B^~C^D)|(C&(~D))|(A);
		assign e = ((~B)&(~D))|(C&(~D));
		assign f = ((~C)&(~D))|(B&(~C))|(B&(~D))|A;
		assign g = (B^C)|(A)|(C&(~D));
		endmodule
		
// testbench
module testbench;
	reg A,B,C,D;
	wire a,b,c,d,e,f,g;
	integer i;
	// instantiate DUT using port order method
	bcd27 b27(A,B,C,D,a,b,c,d,e,f,g);
	initial
		begin
			$monitor($time,"Decimal# = %d , Input=%b%b%b%b, output=%b%b%b%b%b%b%b",i,A,B,C,D,a,b,c,d,e,f,g);
			$dumpfile("bcd27.vcd");
			$dumpvars(0,testbench);
			begin
				for(i=0;i<15;i++)
					begin
					if(i>9)
					{A,B,C,D}= 4'hx;
					else
					{A,B,C,D}=i;
					#5;
					end
					#5 $finish;
					end
		end
	endmodule

DigitalDesign_exercises/Combinational/Exercises/4.9/bcd27.vcd
$date
	Tue Sep 08 14:08:05 2020
$end
$version
	Icarus Verilog
$end
$timescale
	1s
$end
$scope module testbench $end
$var wire 1 ! g $end
$var wire 1 " f $end
$var wire 1 # e $end
$var wire 1 $ d $end
$var wire 1 % c $end
$var wire 1 & b $end
$var wire 1 ' a $end
$var reg 1 ( A $end
$var reg 1 ) B $end
$var reg 1 * C $end
$var reg 1 + D $end
$var integer 32 , i [31:0] $end
$scope module b27 $end
$var wire 1 ( A $end
$var wire 1 ) B $end
$var wire 1 * C $end
$var wire 1 + D $end
$var wire 1 ' a $end
$var wire 1 & b $end
$var wire 1 % c $end
$var wire 1 $ d $end
$var wire 1 # e $end
$var wire 1 " f $end
$var wire 1 ! g $end
$upscope $end
$upscope $end
$enddefinitions $end
#0
$dumpvars
b0 ,
0+
0*
0)
0(
1'
1&
1%
1$
1#
1"
0!
$end
#5
0"
0'
0$
0#
1+
b1 ,
#10
0%
1$
1'
1#
1!
1*
0+
b10 ,
#15
0#
1%
1+
b11 ,
#20
0$
1"
0'
1)
0*
0+
b100 ,
#25
1'
1$
0&
1+
b101 ,
#30
1#
1*
0+
b110 ,
#35
0$
0"
1&
0#
0!
1+
b111 ,
#40
1#
1!
1$
1"
1%
1(
0)
0*
0+
b1000 ,
#45
0#
1+
b1001 ,
#50
x%
x&
x#
x!
x'
x$
x"
x(
x)
x*
x+
b1010 ,
#55
b1011 ,
#60
b1100 ,
#65
b1101 ,
#70
b1110 ,
#75
b1111 ,
