Combinational_Circuits/FullAdder/RippleAdder/rippleadder.v
// 4 bit ripple carry adder. Structural description of a half adder
module half_adder(output S,C, input A,B); // Verilog 2001 convention
	xor(S,A,B);
	and(C,A,B);
endmodule
//Use Half Adders to create full adders- Structural description of FA
module full_adder(output S,C, input A,B,Cin);
	wire S1,C1,D1;
// Instantiate Half adders
	half_adder HA1(S1,C1,A,B);
	half_adder HA2(S,D1,S1,Cin);
	or (C,D1,C1);
endmodule

// We will be creating 4-bit ripple carry Full adder by using Full Adders.
module ripple_adder(output [0:3]S, output Cout,input [0:3]A,B, input Cin);
	wire C1,C2,C3;		// Rippled Carry - refer schematic representation for details.
// Instantiate Full adders to create a 4-bit Ripple carry adder.
	full_adder FA1(S[0],C1,A[0],B[0],Cin);
	full_adder FA2(S[1],C2,A[1],B[1],C1);
	full_adder FA3(S[2],C3,A[2],B[2],C2);
	full_adder FA4(S[3],Cout,A[3],B[3],C3);
endmodule

RippleAdder/testbench_rippleadder.v
// Testbench for ripple adder
module testbenchripple;
	reg [0:3]A,B;
	reg Cin;
	wire [0:3]S;
	wire Cout;
// instantiate DUT module.
	ripple_adder RA1(S,Cout,A,B,Cin);
// Start simulation from here
	initial
		begin
			$dumpfile("ripple_adder.vcd");
			$dumpvars(0,testbenchripple);
			$monitor($time,"A=%h,B=%h,Cin=%b, S=%h,Cout=%b",A,B,Cin,S,Cout);
			#5 A=4'b0;B=4'b0;Cin=1'b0;
			#5 A=4'b0;B=4'b0;Cin=1'b1;
			#5 A=4'b0;B=4'b1;Cin=1'b0;
			#5 A=4'b0;B=4'b1;Cin=1'b1;
			#5 A=4'b1;B=4'b0;Cin=1'b0;
			#5 A=4'b1;B=4'b0;Cin=1'b1;
			#5 A=4'b0;B=4'b1;Cin=1'b0;
			#5 A=4'b1;B=4'b1;Cin=1'b1;
			#5 $finish;
		end
endmodule

Combinational_Circuits/FullAdder/RippleAdder/ripple_adder.vcd
$date
	Mon Aug 31 12:37:57 2020
$end
$version
	Icarus Verilog
$end
$timescale
	1s
$end
$scope module testbenchripple $end
$var wire 4 ! S [0:3] $end
$var wire 1 " Cout $end
$var reg 4 # A [0:3] $end
$var reg 4 $ B [0:3] $end
$var reg 1 % Cin $end
$scope module RA1 $end
$var wire 4 & A [0:3] $end
$var wire 4 ' B [0:3] $end
$var wire 1 % Cin $end
$var wire 4 ( S [0:3] $end
$var wire 1 " Cout $end
$var wire 1 ) C3 $end
$var wire 1 * C2 $end
$var wire 1 + C1 $end
$scope module FA1 $end
$var wire 1 , A $end
$var wire 1 - B $end
$var wire 1 + C $end
$var wire 1 % Cin $end
$var wire 1 . S1 $end
$var wire 1 / S $end
$var wire 1 0 D1 $end
$var wire 1 1 C1 $end
$scope module HA1 $end
$var wire 1 , A $end
$var wire 1 - B $end
$var wire 1 1 C $end
$var wire 1 . S $end
$upscope $end
$scope module HA2 $end
$var wire 1 . A $end
$var wire 1 % B $end
$var wire 1 0 C $end
$var wire 1 / S $end
$upscope $end
$upscope $end
$scope module FA2 $end
$var wire 1 2 A $end
$var wire 1 3 B $end
$var wire 1 * C $end
$var wire 1 + Cin $end
$var wire 1 4 S1 $end
$var wire 1 5 S $end
$var wire 1 6 D1 $end
$var wire 1 7 C1 $end
$scope module HA1 $end
$var wire 1 2 A $end
$var wire 1 3 B $end
$var wire 1 7 C $end
$var wire 1 4 S $end
$upscope $end
$scope module HA2 $end
$var wire 1 4 A $end
$var wire 1 + B $end
$var wire 1 6 C $end
$var wire 1 5 S $end
$upscope $end
$upscope $end
$scope module FA3 $end
$var wire 1 8 A $end
$var wire 1 9 B $end
$var wire 1 ) C $end
$var wire 1 * Cin $end
$var wire 1 : S1 $end
$var wire 1 ; S $end
$var wire 1 < D1 $end
$var wire 1 = C1 $end
$scope module HA1 $end
$var wire 1 8 A $end
$var wire 1 9 B $end
$var wire 1 = C $end
$var wire 1 : S $end
$upscope $end
$scope module HA2 $end
$var wire 1 : A $end
$var wire 1 * B $end
$var wire 1 < C $end
$var wire 1 ; S $end
$upscope $end
$upscope $end
$scope module FA4 $end
$var wire 1 > A $end
$var wire 1 ? B $end
$var wire 1 " C $end
$var wire 1 ) Cin $end
$var wire 1 @ S1 $end
$var wire 1 A S $end
$var wire 1 B D1 $end
$var wire 1 C C1 $end
$scope module HA1 $end
$var wire 1 > A $end
$var wire 1 ? B $end
$var wire 1 C C $end
$var wire 1 @ S $end
$upscope $end
$scope module HA2 $end
$var wire 1 @ A $end
$var wire 1 ) B $end
$var wire 1 B C $end
$var wire 1 A S $end
$upscope $end
$upscope $end
$upscope $end
$upscope $end
$enddefinitions $end
#0
$dumpvars
xC
xB
xA
x@
x?
x>
x=
x<
x;
x:
x9
x8
x7
x6
x5
x4
x3
x2
x1
x0
x/
x.
x-
x,
x+
x*
x)
bx (
bx '
bx &
x%
bx $
bx #
x"
bx !
$end
#5
0;
0A
0*
0)
0"
0/
b0 !
b0 (
05
06
0<
0B
0+
0.
01
04
07
0:
0=
0@
0C
00
0-
03
09
0?
0,
02
08
0>
0%
b0 $
b0 '
b0 #
b0 &
#10
b1000 !
b1000 (
1/
1%
#15
1A
1@
b1 !
b1 (
0/
1?
0%
b1 $
b1 '
#20
b1001 !
b1001 (
1/
1%
#25
b1 !
b1 (
0/
0?
1>
0%
b0 $
b0 '
b1 #
b1 &
#30
b1001 !
b1001 (
1/
1%
#35
b1 !
b1 (
0/
1?
0>
0%
b1 $
b1 '
b0 #
b0 &
#40
0A
1"
0@
1C
b1000 !
b1000 (
1/
1>
1%
b1 #
b1 &
