Sequential_Circuits/ShiftReg/shiftreg_4bit.v
// 4 bit shift register using D Flip Flops

module shiftreg_4bit(clk,clear,A,E);
	input clk, clear,A;
	output reg E;
	reg B,C,D;
	// beginning of behavioral description of the shift register
	always @ (posedge clk or negedge clk)
		begin
			if(!clear)
				begin
				B<=0;
				C<=0;
				D<=0;
				E<=0;
				end
			else
				begin
				E<=D;
				D<=C;
				C<=B;
				B<=A;
				end
		end
	endmodule

Sequential_Circuits/ShiftReg/testbench_shiftreg_4bit.v
// Test bench for shift register 4-bit

module test_bench;
	reg clr,clk,in;
	wire out;

// Instantiate a 4bit shift register
shiftreg_4bit SR(clk, clr, in, out);
// code for testbench begins here
initial
	begin
		clk =1'b0;
		#2 clr =0;
		#3 clr =1;
		end
// All the flip flops have been cleared after the previous operation. Now we need to simulate clock signal.
always #5 clk =~clk;  // This line toggles the clock signal between 0 and 1 every 5 intervals.

// Input test bit pattern - 1100
initial
	begin
		#2;
		repeat(2) // repeat the block for 2 times
			
		begin
			#10 in=0;
			#10 in = 0;
			#10 in = 1;
			#10 in =1;
			end
			end
	initial
		begin
		$dumpfile("test_shifter.vcd");
		$dumpvars(0,test_bench);
		#200 $finish;
	end
endmodule

Sequential_Circuits/ShiftReg/test_shifter.vcd
$date
	Thu Sep 03 18:15:15 2020
$end
$version
	Icarus Verilog
$end
$timescale
	1s
$end
$scope module test_bench $end
$var wire 1 ! out $end
$var reg 1 " clk $end
$var reg 1 # clr $end
$var reg 1 $ in $end
$scope module SR $end
$var wire 1 $ A $end
$var wire 1 # clear $end
$var wire 1 " clk $end
$var reg 1 % B $end
$var reg 1 & C $end
$var reg 1 ' D $end
$var reg 1 ! E $end
$upscope $end
$upscope $end
$enddefinitions $end
#0
$dumpvars
x'
x&
x%
x$
x#
0"
x!
$end
#2
0#
#5
1#
1"
#10
0"
#12
0$
#15
0%
1"
#20
0&
0"
#25
0'
1"
#30
0!
0"
#32
1$
#35
1%
1"
#40
1&
0"
#45
1'
1"
#50
1!
0"
#52
0$
#55
0%
1"
#60
0&
0"
#65
0'
1"
#70
0!
0"
#72
1$
#75
1%
1"
#80
1&
0"
#85
1'
1"
#90
1!
0"
