DigitalDesign_exercises/Combinational/Exercises/4.7/4_7.v
// Verilog model (DataFlow) of a Gray to Binary converter - 2001 style
module gray_to_bin(input w,x,y,z,
					output wire [3:0] a);
	assign a[3]=w;     // Continuous assignment of the net type variable (a)
	xor(a[2],w,x);
	xor(a[1],a[2],y);
	xor(a[0],a[1],z);
endmodule
module testbench;
	wire [3:0]a;
	reg w,x,y,z;
// Instantiate a DUT
gray_to_bin g2b(w,x,y,z,a);

// Stimulus
initial
	begin
		$dumpfile("gray2bin.vcd");
	    $dumpvars(0,testbench);
		$monitor("time=",$time,"w=%b,x=%b,y=%b,z=%b,a=%4b",w,x,y,z,a);
		//case generation - using concatnation
		#5 {w,x,y,z}=4'b0000;
		#5 {w,x,y,z}=4'b0001;
		#5 {w,x,y,z}=4'b0011;
		#5 {w,x,y,z}=4'b0010;
		#5 {w,x,y,z}=4'b0110;
		#5 {w,x,y,z}=4'b0111;
		#5 {w,x,y,z}=4'b0101;
		#5 {w,x,y,z}=4'b0100;
		#5 {w,x,y,z}=4'b1100;
		#5 {w,x,y,z}=4'b1101;
		#5 {w,x,y,z}=4'b1111;
		#5 {w,x,y,z}=4'b1110;
		#5 {w,x,y,z}=4'b1010;
		#5 {w,x,y,z}=4'b1011;
		#5 {w,x,y,z}=4'b1001;
		#5 {w,x,y,z}=4'b1000;
		#5 $finish;
	end
endmodule

DigitalDesign_exercises/Combinational/Exercises/4.7/gray2bin.vcd
$date
	Mon Sep 07 13:15:55 2020
$end
$version
	Icarus Verilog
$end
$timescale
	1s
$end
$scope module testbench $end
$var wire 4 ! a [3:0] $end
$var reg 1 " w $end
$var reg 1 # x $end
$var reg 1 $ y $end
$var reg 1 % z $end
$scope module g2b $end
$var wire 1 " w $end
$var wire 1 # x $end
$var wire 1 $ y $end
$var wire 1 % z $end
$var wire 4 & a [3:0] $end
$upscope $end
$upscope $end
$enddefinitions $end
#0
$dumpvars
bx &
x%
x$
x#
x"
bx !
$end
#5
b0 !
b0 &
0"
0#
0$
0%
#10
b1 !
b1 &
1%
#15
b10 !
b10 &
1$
#20
b11 !
b11 &
0%
#25
b100 !
b100 &
1#
#30
b101 !
b101 &
1%
#35
b110 !
b110 &
0$
#40
b111 !
b111 &
0%
#45
b1000 !
b1000 &
1"
#50
b1001 !
b1001 &
1%
#55
b1010 !
b1010 &
1$
#60
b1011 !
b1011 &
0%
#65
b1100 !
b1100 &
0#
#70
b1101 !
b1101 &
1%
#75
b1110 !
b1110 &
0$
#80
b1111 !
b1111 &
0%
